envclasses/__init__.py
pyenvclasses-0.1.2.dist-info/WHEEL
pyenvclasses-0.1.2.dist-info/METADATA
pyenvclasses-0.1.2.dist-info/RECORD
