Metadata-Version: 2.1
Name: pyenvclasses
Version: 0.1.2
Summary: Wrapper for python dataclasses to read from the environment
License: MIT
Author: Ian Baldwin
Author-email: ian@iantbaldw.in
Requires-Python: >=3.8,<4.0
Classifier: License :: OSI Approved :: MIT License
Classifier: Programming Language :: Python :: 3
Classifier: Programming Language :: Python :: 3.8
Classifier: Programming Language :: Python :: 3.9
